{
  "name": "Enchanter",
  "type": "Class",
  "_id": "1d1686c86d02ec7b",
  "img": "systems/dolmenwood/assets/classes/enchanter.svg",
  "system": {
    "codexUuid": "",
    "classId": "enchanter",
    "requiredKindred": "",
    "primeAbilities": [
      "charisma",
      "intelligence"
    ],
    "hitDice": {
      "die": "1d6",
      "flat": 1
    },
    "xpThresholds": [
      0,
      0,
      1750,
      3500,
      7000,
      14000,
      28000,
      56000,
      112000,
      220000,
      340000,
      460000,
      580000,
      700000,
      820000,
      940000
    ],
    "attackProgression": [
      0,
      0,
      0,
      1,
      1,
      2,
      2,
      3,
      3,
      4,
      4,
      5,
      5,
      6,
      6,
      7
    ],
    "saveProgressions": {
      "doom": [
        0,
        11,
        11,
        10,
        10,
        9,
        9,
        8,
        8,
        7,
        7,
        6,
        6,
        5,
        5,
        4
      ],
      "ray": [
        0,
        12,
        12,
        11,
        11,
        10,
        10,
        9,
        9,
        8,
        8,
        7,
        7,
        6,
        6,
        5
      ],
      "hold": [
        0,
        13,
        13,
        12,
        12,
        11,
        11,
        10,
        10,
        9,
        9,
        8,
        8,
        7,
        7,
        6
      ],
      "blast": [
        0,
        16,
        16,
        15,
        15,
        14,
        14,
        13,
        13,
        12,
        12,
        11,
        11,
        10,
        10,
        9
      ],
      "spell": [
        0,
        14,
        14,
        13,
        13,
        12,
        12,
        11,
        11,
        10,
        10,
        9,
        9,
        8,
        8,
        7
      ]
    },
    "skillProgressions": {},
    "spellProgression": [],
    "spellType": "none",
    "combatAptitude": "non-martial",
    "hasCombatTalents": false,
    "hasHolyOrder": false,
    "canTwoWeaponFight": false,
    "hasBackstab": false,
    "traits": {
      "passive": [
        {
          "id": "holySpellFailure",
          "nameKey": "DOLMEN.Traits.HolySpellFailure",
          "descKey": "DOLMEN.Traits.HolySpellFailureDesc",
          "traitType": "active",
          "rollable": true,
          "rollFormula": "1d6",
          "rollTarget": 2
        }
      ]
    }
  },
  "effects": [],
  "folder": null,
  "sort": 0,
  "ownership": {
    "default": 0
  },
  "flags": {},
  "_stats": {
    "compendiumSource": null,
    "duplicateSource": null,
    "coreVersion": "13.351",
    "systemId": "dolmenwood",
    "systemVersion": "0.2.0",
    "createdTime": 1770843306205,
    "modifiedTime": 1770843306205,
    "lastModifiedBy": null
  },
  "_key": "!items!1d1686c86d02ec7b"
}